{
	"$schema": "https://raw.githubusercontent.com/0u73r-h34v3n/opengamesdatabase/refs/heads/master/shared/metadata_schema.json",
	"locales": ["ES", "FR", "PT"],
	"name": "Best of Mahjong",
	"publishers": ["cosmigo"],
	"release_date": "January 15, 2015",
	"serial_number": "JVME",
	"synopsis": "Relax your mind with the ancient game of tiles. Best of Mahjong features 404 layouts of the traditional tile-matching game in 3D, each with millions of different shuffles to play. The game's style and interface has been designed for easy and intuitive operation with the stylus or +Control Pad. The graphics can be customized with fabulous tile-sets and backgrounds. Sit back, relax and enjoy the endless challenge with this Mahjong game collection."
}
