{
	"$schema": "https://raw.githubusercontent.com/0u73r-h34v3n/opengamesdatabase/refs/heads/master/shared/metadata_scheme.json",
	"developers": ["Bitstep"],
	"genres": ["Action", "Fighting"],
	"name": "Ultraman",
	"publishers": ["Bandai"],
	"regions": ["NTSC-J"],
	"synopsis": "Gigantic and treacherous aliens are invading Earth. They're destroying our cities and leaving a path of chaos around the planet. There is one humongous hero powerful enough to eradicate these creatures... Ultraman!!! Part human, part super being, he's got what it takes to eliminate the evil aliens once and for all. Ultraman uses his special weapons along with martial arts, wresting, and street brawling skills to fight off each attacking monster.   This game utilizes its 16-Bit power to its fullest. Really large characters, detailed landscapes, realistic sound effect and music that are gonna know you out!"
}
