{
	"$schema": "https://raw.githubusercontent.com/0u73r-h34v3n/opengamesdatabase/refs/heads/master/shared/metadata_schema.json",
	"developers": ["Inteligente Systems"],
	"genres": ["Action", "Demo", "Party"],
	"name": "WarioWare: Touched! (Demo) ",
	"publishers": ["Nintendo"],
	"ratings": [
		{
			"name": "ESRB",
			"rating": "E"
		}
	],
	"release_date": "January 1, 2004",
	"serial_number": "A22E",
	"synopsis": "Wario and his wacky companions have returned to transform your touch screen into a playground of possibilities, with 180 wild microgames."
}
