{
	"$schema": "https://raw.githubusercontent.com/0u73r-h34v3n/opengamesdatabase/refs/heads/master/shared/metadata_schema.json",
	"developers": ["Princess Soft"],
	"genres": ["Visual Novel"],
	"name": "Finalist",
	"publishers": ["Princess Soft"],
	"regions": ["NTSC-J"],
	"synopsis": "Finalist's story takes place in a college town somewhere in Japan. The protagonist of the story, Yoshiki Shirasagi, is a male high school student. When he entered high school, he was mistakenly given a room in the girl's dormitory due to his feminine name. Throughout the game Yoshiki meets many of the girls who live in the same dormitory."
}
