{
	"$schema": "https://raw.githubusercontent.com/0u73r-h34v3n/opengamesdatabase/refs/heads/master/shared/metadata_schema.json",
	"developers": ["Creatures Inc"],
	"genres": ["Action", "Adventure", "Point-And-Click"],
	"locales": ["ES"],
	"name": "Detective Pikachu",
	"publishers": ["Nintendo"],
	"ratings": [
		{
			"name": "PEGI",
			"rating": "3"
		}
	],
	"release_date": "January 1, 2018",
	"serial_number": "A98P",
	"synopsis": "Put your detective hat on – it’s time to crack the case of a boy’s missing father in Detective Pikachu, a unique adventure game filled with beloved Pokémon, only on Nintendo 3DS family systems. Follow the story of Tim Goodman, an 18-year-old university student with a strong sense of justice, and form an unlikely partnership with a peculiar talking Pikachu! Gather evidence, interview witnesses, and piece together a variety of clues to unravel the many mysteries surrounding Ryme City."
}
