{
	"$schema": "https://raw.githubusercontent.com/0u73r-h34v3n/opengamesdatabase/refs/heads/master/shared/metadata_scheme.json",
	"developers": ["D3Publisher"],
	"genres": ["Gambling"],
	"name": "CR Shinseiki Evangelion: Saigo no Mono",
	"publishers": ["D3Publisher"],
	"regions": ["NTSC-J"],
	"synopsis": "A pachinko machine simulator themed by an episode of the anime series Neon Genesis Evangelion. The pachinko is presented in 3D, the player can zoom, move and rotate the machine as he likes. "
}
